rasa_recognizers_text_extractor/__init__.py
rasa_recognizers_text_extractor/extractor.py
rasa_recognizers_text_extractor-0.1.1.dist-info/AUTHORS.rst
rasa_recognizers_text_extractor-0.1.1.dist-info/LICENSE
rasa_recognizers_text_extractor-0.1.1.dist-info/METADATA
rasa_recognizers_text_extractor-0.1.1.dist-info/WHEEL
rasa_recognizers_text_extractor-0.1.1.dist-info/top_level.txt
rasa_recognizers_text_extractor-0.1.1.dist-info/RECORD
