Metadata-Version: 2.1
Name: rasa-recognizers-text-extractor
Version: 0.1.1
Summary: A Rasa NLU module for extracting entities using Microsoft's Recognizers Text library
Home-page: https://github.com/botisan-ai/rasa-recognizers-text-extractor
Author: Simon Liang
Author-email: simon@x-tech.io
License: MIT license
Keywords: rasa-recognizers-text-extractor
Classifier: Development Status :: 2 - Pre-Alpha
Classifier: Intended Audience :: Developers
Classifier: License :: OSI Approved :: MIT License
Classifier: Natural Language :: English
Classifier: Programming Language :: Python :: 3
Classifier: Programming Language :: Python :: 3.7
Classifier: Programming Language :: Python :: 3.8
Classifier: Programming Language :: Python :: 3.9
Requires-Python: >=3.7,<3.10
License-File: LICENSE
License-File: AUTHORS.rst
Requires-Dist: rasa (>=3)
